{"name":"Puzzle","className":"DataModel","filePaths":["default.project.json"],"children":[{"name":"Lighting","className":"Lighting"},{"name":"ReplicatedStorage","className":"ReplicatedStorage","children":[{"name":"Prefabs","className":"Folder","children":[{"name":"Grid","className":"Folder"},{"name":"Piece","className":"Folder"},{"name":"PlayerList","className":"Folder"}]},{"name":"Remotes","className":"Folder","children":[{"name":"BroadcastNewBoard","className":"RemoteEvent"},{"name":"SubmitSolution","className":"RemoteEvent"},{"name":"UpdateFinishers","className":"RemoteEvent"}]},{"name":"Shared","className":"Folder","children":[{"name":"BoardService","className":"ModuleScript","filePaths":["src/shared\\BoardService\\init.luau"],"children":[{"name":"Config","className":"ModuleScript","filePaths":["src/shared\\BoardService\\Config.luau"]},{"name":"Utils","className":"ModuleScript","filePaths":["src/shared\\BoardService\\Utils.luau"]}]},{"name":"Client","className":"Folder","children":[{"name":"Input","className":"Folder","children":[{"name":"Selector","className":"ModuleScript","filePaths":["src/shared\\Client\\Input\\Selector.luau"]}]},{"name":"Interface","className":"Folder","children":[{"name":"Board","className":"ModuleScript","filePaths":["src/shared\\Client\\Interface\\Board\\init.luau"],"children":[{"name":"Config","className":"ModuleScript","filePaths":["src/shared\\Client\\Interface\\Board\\Config.luau"]},{"name":"Timer","className":"ModuleScript","filePaths":["src/shared\\Client\\Interface\\Board\\Timer.luau"]}]},{"name":"PlayerList","className":"ModuleScript","filePaths":["src/shared\\Client\\Interface\\PlayerList\\init.luau"],"children":[{"name":"Config","className":"ModuleScript","filePaths":["src/shared\\Client\\Interface\\PlayerList\\Config.luau"]}]},{"name":"Reserve","className":"ModuleScript","filePaths":["src/shared\\Client\\Interface\\Reserve.luau"]},{"name":"Utils","className":"ModuleScript","filePaths":["src/shared\\Client\\Interface\\Utils.luau"]}]}]},{"name":"PieceService","className":"ModuleScript","filePaths":["src/shared\\PieceService.luau"]},{"name":"Types","className":"ModuleScript","filePaths":["src/shared\\Types.luau"]}]}]},{"name":"ServerScriptService","className":"ServerScriptService","children":[{"name":"Server","className":"Script","filePaths":["src/server\\init.server.luau"],"children":[{"name":"Game","className":"ModuleScript","filePaths":["src/server\\Game\\init.luau"],"children":[{"name":"Dices","className":"ModuleScript","filePaths":["src/server\\Game\\Dices.luau"]},{"name":"Config","className":"ModuleScript","filePaths":["src/server\\Game\\Config.luau"]}]}]}]},{"name":"SoundService","className":"SoundService"},{"name":"StarterPlayer","className":"StarterPlayer","children":[{"name":"StarterPlayerScripts","className":"StarterPlayerScripts","children":[{"name":"Client","className":"LocalScript","filePaths":["src/client\\init.client.luau"]}]}]},{"name":"Workspace","className":"Workspace","children":[{"name":"Baseplate","className":"Part"}]}]}